creativiousutilities/__init__.py
creativiousutilities/test.py
creativiousutilities/config/__init__.py
creativiousutilities/discord/__init__.py
creativiousutilities/discord/ui/__init__.py
creativiousutilities/gmod/__init__.py
creativiousutilities/gmod/bLogs/__init__.py
creativiousutilities/logging/__init__.py
creativiousutilities/sql/__init__.py
creativiousutilities-2.1.1.dist-info/METADATA
creativiousutilities-2.1.1.dist-info/WHEEL
creativiousutilities-2.1.1.dist-info/licenses/LICENSE
creativiousutilities-2.1.1.dist-info/RECORD
