Metadata-Version: 2.1
Name: creativiousUtilities
Version: 2.1.1
Summary: Experimental and likely to break by update
Author-email: Creativious <timothy@creativious.net>
Classifier: Operating System :: OS Independent
Classifier: Programming Language :: Python :: 3
Requires-Python: >=3.10
